pytest_ngsfixtures/__init__.py
pytest_ngsfixtures/_version.py
pytest_ngsfixtures/config.py
pytest_ngsfixtures/os.py
pytest_ngsfixtures/plugin.py
pytest_ngsfixtures/shell.py
pytest_ngsfixtures/utils.py
pytest_ngsfixtures/data/Snakefile
pytest_ngsfixtures/data/ref/ERCC_spikes.gb
pytest_ngsfixtures/data/ref/Makefile
pytest_ngsfixtures/data/ref/known.scaffolds.vcf.gz
pytest_ngsfixtures/data/ref/known.scaffolds.vcf.gz.tbi
pytest_ngsfixtures/data/ref/pAcGFP1-N1.fasta
pytest_ngsfixtures/data/ref/scaffolds-targets.bed
pytest_ngsfixtures/data/ref/scaffolds-targets.interval_list
pytest_ngsfixtures/data/ref/scaffolds-transcripts-tiny.bed12
pytest_ngsfixtures/data/ref/scaffolds-transcripts-tiny.genePred
pytest_ngsfixtures/data/ref/scaffolds-transcripts-tiny.gtf
pytest_ngsfixtures/data/ref/scaffolds-transcripts-tiny.refFlat
pytest_ngsfixtures/data/ref/scaffolds-transcripts.bed12
pytest_ngsfixtures/data/ref/scaffolds-transcripts.genePred
pytest_ngsfixtures/data/ref/scaffolds-transcripts.gtf
pytest_ngsfixtures/data/ref/scaffolds-transcripts.refFlat
pytest_ngsfixtures/data/ref/scaffolds.bed
pytest_ngsfixtures/data/ref/scaffolds.chrom.sizes
pytest_ngsfixtures/data/ref/scaffolds.dict
pytest_ngsfixtures/data/ref/scaffolds.fa
pytest_ngsfixtures/data/ref/scaffolds.fa.fai
pytest_ngsfixtures/data/ref/scaffolds.interval_list
pytest_ngsfixtures/data/ref/scaffoldsN.bed
pytest_ngsfixtures/data/ref/scaffoldsN.chrom.sizes
pytest_ngsfixtures/data/ref/scaffoldsN.dict
pytest_ngsfixtures/data/ref/scaffoldsN.fa
pytest_ngsfixtures/data/ref/scaffoldsN.fa.fai
pytest_ngsfixtures/data/seq/CHS.HG00512_1.fastq.gz
pytest_ngsfixtures/data/seq/CHS.HG00512_2.fastq.gz
pytest_ngsfixtures/data/seq/CHS.HG00513_1.fastq.gz
pytest_ngsfixtures/data/seq/CHS.HG00513_2.fastq.gz
pytest_ngsfixtures/data/seq/CHS_1.fastq.gz
pytest_ngsfixtures/data/seq/CHS_2.fastq.gz
pytest_ngsfixtures/data/seq/PUR.HG00731.A_1.fastq.gz
pytest_ngsfixtures/data/seq/PUR.HG00731.A_2.fastq.gz
pytest_ngsfixtures/data/seq/PUR.HG00731.B_1.fastq.gz
pytest_ngsfixtures-0.8.1.dist-info/AUTHORS.rst
pytest_ngsfixtures-0.8.1.dist-info/LICENSE
pytest_ngsfixtures-0.8.1.dist-info/METADATA
pytest_ngsfixtures-0.8.1.dist-info/WHEEL
pytest_ngsfixtures-0.8.1.dist-info/entry_points.txt
pytest_ngsfixtures-0.8.1.dist-info/top_level.txt
pytest_ngsfixtures-0.8.1.dist-info/RECORD
