Metadata-Version: 2.1
Name: pytest-ngsfixtures
Version: 0.8.1
Summary: pytest ngs fixtures
Home-page: https://github.com/percyfal/pytest-ngsfixtures
Author: Per Unneberg
Author-email: per.unneberg@scilifelab.se
License: GNU General Public License v3
Keywords: pytest,ngs
Platform: UNKNOWN
Classifier: Framework :: Pytest
Classifier: Development Status :: 2 - Pre-Alpha
Classifier: Intended Audience :: Developers
Classifier: License :: OSI Approved :: GNU General Public License v3 (GPLv3)
Classifier: Natural Language :: English
Classifier: Programming Language :: Python :: 3
Classifier: Programming Language :: Python :: 3.5
Classifier: Programming Language :: Python :: 3.6
Classifier: Programming Language :: Python :: 3.7
Classifier: Topic :: Utilities
Requires-Dist: pytest (>=5.0.0)
Requires-Dist: pyyaml
